hellouser123/__init__.py
hellouser123/hello.py
hellouser123-0.0.1.dist-info/METADATA
hellouser123-0.0.1.dist-info/WHEEL
hellouser123-0.0.1.dist-info/top_level.txt
hellouser123-0.0.1.dist-info/RECORD
