Metadata-Version: 2.1
Name: hellouser123
Version: 0.0.1
Summary: Hello
Home-page: https://github.com/tasksss/hello
Author: astghm
Author-email: astghik.manvelyan@gmail.com
License: UNKNOWN
Platform: UNKNOWN
Classifier: Programming Language :: Python :: 3
Classifier: License :: OSI Approved :: MIT License
Classifier: Operating System :: OS Independent
Requires-Python: >=3.6
